{"_type":"export","__export_format":4,"__export_date":"2024-07-15T15:56:53.118Z","__export_source":"insomnia.desktop.app:v2022.7.5","resources":[{"_id":"req_b479b20d42b4458c8acd6e5f2db8112f","parentId":"fld_530d5c10bf3c4bacbbc1f224e5de356c","modified":1721056356388,"created":1721056317168,"url":"localhost:8080/chromosome/targetPopulation/1","name":"Get Experimental Chromosomes By TargetPopulation","description":"","method":"GET","body":{},"parameters":[],"headers":[],"authentication":{},"metaSortKey":-1721056317168,"isPrivate":false,"settingStoreCookies":true,"settingSendCookies":true,"settingDisableRenderRequestBody":false,"settingEncodeUrl":true,"settingRebuildPath":true,"settingFollowRedirects":"global","_type":"request"},{"_id":"fld_530d5c10bf3c4bacbbc1f224e5de356c","parentId":"wrk_e5fc8cd612ae4044a330c031486500ad","modified":1721055460058,"created":1721055460058,"name":"Chromosome","description":"","environment":{},"environmentPropertyOrder":null,"metaSortKey":-1721055460058,"_type":"request_group"},{"_id":"wrk_e5fc8cd612ae4044a330c031486500ad","parentId":null,"modified":1721054681611,"created":1721054681611,"name":"Distributed Differential Evolution","description":"","scope":"collection","_type":"workspace"},{"_id":"req_533e3a0c202942cca3479beb407d838f","parentId":"fld_530d5c10bf3c4bacbbc1f224e5de356c","modified":1721056511027,"created":1721055462255,"url":"localhost:8080/chromosome/11","name":"Get Chromosome By Id","description":"","method":"GET","body":{},"parameters":[],"headers":[],"authentication":{},"metaSortKey":-1721055462255,"isPrivate":false,"settingStoreCookies":true,"settingSendCookies":true,"settingDisableRenderRequestBody":false,"settingEncodeUrl":true,"settingRebuildPath":true,"settingFollowRedirects":"global","_type":"request"},{"_id":"req_86a8901b03814a50a1be932e0cf59acd","parentId":"fld_530d5c10bf3c4bacbbc1f224e5de356c","modified":1721057786528,"created":1721055675757,"url":"localhost:8080/chromosome/{% response 'body', 'req_571bf2cb303f464885fe050ce3a72014', 'b64::JC5jaHJvbW9zb21lLmlk::46b', 'never', 60 %}/evaluationResult","name":"Publish Evaluation Result","description":"","method":"POST","body":{"mimeType":"application/json","text":"{\n\t\"fitness\": 20,\n\t\"evaluationId\": \"{% response 'body', 'req_571bf2cb303f464885fe050ce3a72014', 'b64::JC5jaHJvbW9zb21lLmV2YWx1YXRpb25JZA==::46b', 'never', 60 %}\"\n}"},"parameters":[],"headers":[{"name":"Content-Type","value":"application/json"}],"authentication":{},"metaSortKey":-1721055462205,"isPrivate":false,"settingStoreCookies":true,"settingSendCookies":true,"settingDisableRenderRequestBody":false,"settingEncodeUrl":true,"settingRebuildPath":true,"settingFollowRedirects":"global","_type":"request"},{"_id":"req_906b97c1001a4d6992d0f976a9e149b5","parentId":"fld_98a86f43cc1b47cdb34d053cad72ce67","modified":1721055173152,"created":1721054990618,"url":"localhost:8080/population/1","name":"Get Population By Id","description":"","method":"GET","body":{},"parameters":[],"headers":[],"authentication":{},"metaSortKey":-1721055170932,"isPrivate":false,"settingStoreCookies":true,"settingSendCookies":true,"settingDisableRenderRequestBody":false,"settingEncodeUrl":true,"settingRebuildPath":true,"settingFollowRedirects":"global","_type":"request"},{"_id":"fld_98a86f43cc1b47cdb34d053cad72ce67","parentId":"wrk_e5fc8cd612ae4044a330c031486500ad","modified":1721055088937,"created":1721055088937,"name":"Population","description":"","environment":{},"environmentPropertyOrder":null,"metaSortKey":-1721055088937,"_type":"request_group"},{"_id":"req_51dac8064ae64dd584f0d6fa9ad73025","parentId":"fld_fe813aca663143b0a70daf8574bba323","modified":1721057934274,"created":1721054701403,"url":"localhost:8080/optimizationRun","name":"Create Optimization Run","description":"","method":"POST","body":{"mimeType":"application/json","text":"{\n\t\"objectiveFunctionId\": 1,\n\t\"populationSize\": 2,\n\t\"crossOverProbability\": 0.85,\n\t\"perturbationFactor\": 0.8,\n\t\"maxGenerations\": 10,\n\t\"objectiveFunctionEvaluationTimeoutSeconds\": 30,\n\t\"chromosomeElementDetails\": [\n\t\t{\n\t\t\t\"name\": \"teste element 1\",\n\t\t\t\"position\": 0,\n\t\t\t\"lowerBoundary\": -1.0,\n\t\t\t\"upperBoundary\": 0.0,\n\t\t\t\"description\": \"first element, used for test pourposes\"\n\t\t},\n\t\t{\n\t\t\t\"name\": \"teste element 2\",\n\t\t\t\"position\": 1,\n\t\t\t\"lowerBoundary\": 0.0,\n\t\t\t\"upperBoundary\": 1.0,\n\t\t\t\"description\": \"second element, used for test pourposes\"\n\t\t}\n\t]\n}"},"parameters":[],"headers":[{"name":"Content-Type","value":"application/json"}],"authentication":{},"metaSortKey":-1721055106288.2812,"isPrivate":false,"settingStoreCookies":true,"settingSendCookies":true,"settingDisableRenderRequestBody":false,"settingEncodeUrl":true,"settingRebuildPath":true,"settingFollowRedirects":"global","_type":"request"},{"_id":"fld_fe813aca663143b0a70daf8574bba323","parentId":"wrk_e5fc8cd612ae4044a330c031486500ad","modified":1721055083617,"created":1721055083617,"name":"Optimization Run","description":"","environment":{},"environmentPropertyOrder":null,"metaSortKey":-1721055083617,"_type":"request_group"},{"_id":"req_482ed89c74e04b179618df2bea5c6bd4","parentId":"fld_fe813aca663143b0a70daf8574bba323","modified":1721057798682,"created":1721054963371,"url":"localhost:8080/optimizationRun/1","name":"Get Optimization Run By Id","description":"","method":"GET","body":{},"parameters":[],"headers":[],"authentication":{},"metaSortKey":-1721055105821.8281,"isPrivate":false,"settingStoreCookies":true,"settingSendCookies":true,"settingDisableRenderRequestBody":false,"settingEncodeUrl":true,"settingRebuildPath":true,"settingFollowRedirects":"global","_type":"request"},{"_id":"req_571bf2cb303f464885fe050ce3a72014","parentId":"fld_fe813aca663143b0a70daf8574bba323","modified":1721055122167,"created":1721055033603,"url":"localhost:8080/optimizationRun/1/chromosome/notEvaluated","name":"Get Not Evaluated Chromosome","description":"","method":"GET","body":{},"parameters":[],"headers":[],"authentication":{},"metaSortKey":-1721055105355.375,"isPrivate":false,"settingStoreCookies":true,"settingSendCookies":true,"settingDisableRenderRequestBody":false,"settingEncodeUrl":true,"settingRebuildPath":true,"settingFollowRedirects":"global","_type":"request"},{"_id":"req_f75130374b4e48379b9f34ebcded850d","parentId":"fld_fe813aca663143b0a70daf8574bba323","modified":1721055160300,"created":1721055099136,"url":"localhost:8080/optimizationRun/1/populations","name":"Get Optimization Run Populations","description":"","method":"GET","body":{},"parameters":[],"headers":[],"authentication":{},"metaSortKey":-1721055099136,"isPrivate":false,"settingStoreCookies":true,"settingSendCookies":true,"settingDisableRenderRequestBody":false,"settingEncodeUrl":true,"settingRebuildPath":true,"settingFollowRedirects":"global","_type":"request"},{"_id":"env_c9bba5ba1a1527ee3dfd7e492daccbc4a8af067b","parentId":"wrk_e5fc8cd612ae4044a330c031486500ad","modified":1721054681615,"created":1721054681615,"name":"Base Environment","data":{},"dataPropertyOrder":null,"color":null,"isPrivate":false,"metaSortKey":1721054681615,"_type":"environment"},{"_id":"jar_c9bba5ba1a1527ee3dfd7e492daccbc4a8af067b","parentId":"wrk_e5fc8cd612ae4044a330c031486500ad","modified":1721054681620,"created":1721054681620,"name":"Default Jar","cookies":[],"_type":"cookie_jar"},{"_id":"spc_2794e978cc6542b3a171b56e4c66791b","parentId":"wrk_e5fc8cd612ae4044a330c031486500ad","modified":1721054681612,"created":1721054681612,"fileName":"Distributed Differential Evolution","contents":"","contentType":"yaml","_type":"api_spec"}]}